{
  "entrypoints": [
    "main"
  ],
  "origins": {
    "1169": [
      1176,
      1245,
      1331,
      1398,
      2453,
      2548,
      2983,
      3068,
      3626,
      3706,
      4162,
      7426,
      7560,
      8055,
      8635,
      8810,
      1169
    ],
    "1176": [
      1169,
      1245,
      1331,
      1398,
      2453,
      2548,
      2983,
      3068,
      3626,
      3706,
      7426,
      7560,
      8055,
      8635,
      8810,
      1176
    ],
    "1245": [
      1169,
      1176,
      1331,
      2983,
      3068,
      7560,
      8055,
      1245
    ],
    "1303": [
      7560,
      1303
    ],
    "1331": [
      1169,
      1176,
      1245,
      1331
    ],
    "1398": [
      1169,
      1176,
      1398
    ],
    "1946": [
      1946
    ],
    "2130": [
      2130
    ],
    "2237": [
      2237
    ],
    "2376": [
      2376
    ],
    "2453": [
      1169,
      1176,
      2548,
      2983,
      7560,
      8055,
      2453
    ],
    "2548": [
      1169,
      1176,
      2453,
      2983,
      4741,
      7560,
      8055,
      8810,
      2548
    ],
    "2843": [
      2843
    ],
    "2901": [
      1869,
      6061,
      8401,
      2901
    ],
    "2925": [
      7560,
      2925
    ],
    "2983": [
      1169,
      1176,
      1245,
      2453,
      2548,
      3068,
      3626,
      7560,
      8055,
      8635,
      8810,
      2983
    ],
    "3068": [
      1169,
      1176,
      1245,
      2983,
      7560,
      8055,
      3068
    ],
    "3626": [
      1169,
      1176,
      2983,
      7426,
      7560,
      8055,
      8635,
      3626
    ],
    "3706": [
      1169,
      1176,
      3706
    ],
    "4162": [
      1169,
      7560,
      8055,
      4162
    ],
    "4741": [
      2548,
      7560,
      8055,
      4741
    ],
    "4943": [
      4943
    ],
    "6420": [
      6420
    ],
    "6788": [
      6788
    ],
    "6803": [
      6803
    ],
    "7426": [
      1169,
      1176,
      3626,
      7426
    ],
    "7560": [
      1169,
      1176,
      1245,
      1303,
      2453,
      2548,
      2925,
      2983,
      3068,
      3626,
      4162,
      4741,
      8055,
      8635,
      8810,
      7560
    ],
    "8055": [
      1169,
      1176,
      1245,
      2453,
      2548,
      2983,
      3068,
      3626,
      4162,
      4741,
      7560,
      8635,
      8810,
      8055
    ],
    "8478": [
      8478
    ],
    "8635": [
      1169,
      1176,
      2983,
      3626,
      7560,
      8055,
      8635
    ],
    "8810": [
      1169,
      1176,
      2548,
      2983,
      7560,
      8055,
      8810
    ],
    "8869": [
      8869
    ],
    "9689": [
      9689
    ],
    "17896441": [
      1869,
      2901,
      8401
    ],
    "main": [
      1869,
      5354,
      8792
    ],
    "runtime~main": [
      1869,
      8792,
      5354
    ],
    "04076d1f": [
      4707
    ],
    "0e1005aa": [
      722
    ],
    "0ec67276": [
      8889
    ],
    "0f8cca8e": [
      1219
    ],
    "10fc90d5": [
      4059
    ],
    "1e141796": [
      1131
    ],
    "1f391b9e": [
      1869,
      2901,
      6061
    ],
    "20d0fad5": [
      8119
    ],
    "46181d78": [
      724
    ],
    "5931b71a": [
      7502
    ],
    "5bae6ed6": [
      1085
    ],
    "5e95c892": [
      9647
    ],
    "6d49b80b": [
      7532
    ],
    "7ea72f97": [
      5815
    ],
    "8c5da4da": [
      453
    ],
    "a2065270": [
      1816
    ],
    "a7456010": [
      1235
    ],
    "a7bd4aaa": [
      7098
    ],
    "a94703ab": [
      1869,
      9048
    ],
    "aba21aa0": [
      5742
    ],
    "b2c83e6f": [
      1869,
      1734
    ],
    "bbc370a0": [
      1869,
      9319
    ],
    "cc1bb06d": [
      6908
    ],
    "d0323e98": [
      251
    ],
    "e083d970": [
      2503
    ],
    "f3976560": [
      1869,
      7795
    ],
    "styles": [
      1734,
      2901,
      5354,
      6061,
      7795,
      8401,
      8792,
      9048,
      9319,
      1869
    ]
  },
  "assets": {
    "251": {
      "js": [
        {
          "file": "assets/js/d0323e98.0691eb8f.js",
          "hash": "5cd7fecf18920da8",
          "publicPath": "/docs/assets/js/d0323e98.0691eb8f.js"
        }
      ]
    },
    "453": {
      "js": [
        {
          "file": "assets/js/8c5da4da.a9db9e85.js",
          "hash": "8a76a32530e122f7",
          "publicPath": "/docs/assets/js/8c5da4da.a9db9e85.js"
        }
      ]
    },
    "722": {
      "js": [
        {
          "file": "assets/js/0e1005aa.96f9a866.js",
          "hash": "6d5c0681ec493796",
          "publicPath": "/docs/assets/js/0e1005aa.96f9a866.js"
        }
      ]
    },
    "724": {
      "js": [
        {
          "file": "assets/js/46181d78.7efd8127.js",
          "hash": "aff46b11a6a41a0f",
          "publicPath": "/docs/assets/js/46181d78.7efd8127.js"
        }
      ]
    },
    "1085": {
      "js": [
        {
          "file": "assets/js/5bae6ed6.70cdab90.js",
          "hash": "038837e54aeaaf25",
          "publicPath": "/docs/assets/js/5bae6ed6.70cdab90.js"
        }
      ]
    },
    "1131": {
      "js": [
        {
          "file": "assets/js/1e141796.ade85300.js",
          "hash": "a99b2d889f36a73f",
          "publicPath": "/docs/assets/js/1e141796.ade85300.js"
        }
      ]
    },
    "1169": {
      "js": [
        {
          "file": "assets/js/1169.2f7c8835.js",
          "hash": "844f361c7882bf93",
          "publicPath": "/docs/assets/js/1169.2f7c8835.js"
        }
      ]
    },
    "1176": {
      "js": [
        {
          "file": "assets/js/1176.e2530ce7.js",
          "hash": "fa617df6112333ae",
          "publicPath": "/docs/assets/js/1176.e2530ce7.js"
        }
      ]
    },
    "1219": {
      "js": [
        {
          "file": "assets/js/0f8cca8e.744539d6.js",
          "hash": "346f5389d02e5523",
          "publicPath": "/docs/assets/js/0f8cca8e.744539d6.js"
        }
      ]
    },
    "1235": {
      "js": [
        {
          "file": "assets/js/a7456010.5f9bbb01.js",
          "hash": "db267b9a2f33d687",
          "publicPath": "/docs/assets/js/a7456010.5f9bbb01.js"
        }
      ]
    },
    "1245": {
      "js": [
        {
          "file": "assets/js/1245.65709502.js",
          "hash": "48ec6c7b22da8181",
          "publicPath": "/docs/assets/js/1245.65709502.js"
        }
      ]
    },
    "1303": {
      "js": [
        {
          "file": "assets/js/1303.a67daacf.js",
          "hash": "2a41d9ae01e35f4b",
          "publicPath": "/docs/assets/js/1303.a67daacf.js"
        }
      ]
    },
    "1331": {
      "js": [
        {
          "file": "assets/js/1331.a7ea7c97.js",
          "hash": "a12c57b7e98ee7d0",
          "publicPath": "/docs/assets/js/1331.a7ea7c97.js"
        }
      ]
    },
    "1398": {
      "js": [
        {
          "file": "assets/js/1398.553304ef.js",
          "hash": "97eac0d47fce73c7",
          "publicPath": "/docs/assets/js/1398.553304ef.js"
        }
      ]
    },
    "1734": {
      "js": [
        {
          "file": "assets/js/b2c83e6f.1945f130.js",
          "hash": "6060fe1a401c5d99",
          "publicPath": "/docs/assets/js/b2c83e6f.1945f130.js"
        }
      ]
    },
    "1816": {
      "js": [
        {
          "file": "assets/js/a2065270.9431fefe.js",
          "hash": "a8d3656058822e30",
          "publicPath": "/docs/assets/js/a2065270.9431fefe.js"
        }
      ]
    },
    "1869": {
      "css": [
        {
          "file": "assets/css/styles.b573ec2f.css",
          "hash": "a8bf0c9abfc07f72",
          "publicPath": "/docs/assets/css/styles.b573ec2f.css"
        }
      ]
    },
    "1946": {
      "js": [
        {
          "file": "assets/js/1946.676ae20a.js",
          "hash": "e48cbc3fd09dada5",
          "publicPath": "/docs/assets/js/1946.676ae20a.js"
        }
      ]
    },
    "2130": {
      "js": [
        {
          "file": "assets/js/2130.6c9f8cee.js",
          "hash": "3ff1d3649d710281",
          "publicPath": "/docs/assets/js/2130.6c9f8cee.js"
        }
      ]
    },
    "2237": {
      "js": [
        {
          "file": "assets/js/2237.c08f4c3d.js",
          "hash": "7dee733d8c736080",
          "publicPath": "/docs/assets/js/2237.c08f4c3d.js"
        }
      ]
    },
    "2376": {
      "js": [
        {
          "file": "assets/js/2376.35a9e0fb.js",
          "hash": "e6461afa139dd4ec",
          "publicPath": "/docs/assets/js/2376.35a9e0fb.js"
        }
      ]
    },
    "2453": {
      "js": [
        {
          "file": "assets/js/2453.fbf2ef40.js",
          "hash": "cbc9b7cb94cfcb85",
          "publicPath": "/docs/assets/js/2453.fbf2ef40.js"
        }
      ]
    },
    "2503": {
      "js": [
        {
          "file": "assets/js/e083d970.f93e4c60.js",
          "hash": "c62ab63edf0d734e",
          "publicPath": "/docs/assets/js/e083d970.f93e4c60.js"
        }
      ]
    },
    "2548": {
      "js": [
        {
          "file": "assets/js/2548.e8601867.js",
          "hash": "d0f6b4ba57ce2773",
          "publicPath": "/docs/assets/js/2548.e8601867.js"
        }
      ]
    },
    "2843": {
      "js": [
        {
          "file": "assets/js/2843.222088a4.js",
          "hash": "7687c4f0f31c4090",
          "publicPath": "/docs/assets/js/2843.222088a4.js"
        }
      ]
    },
    "2901": {
      "js": [
        {
          "file": "assets/js/2901.a3d1f719.js",
          "hash": "9200540fd0f7f23b",
          "publicPath": "/docs/assets/js/2901.a3d1f719.js"
        }
      ]
    },
    "2925": {
      "js": [
        {
          "file": "assets/js/2925.76671e8e.js",
          "hash": "c39b1b872186ae8e",
          "publicPath": "/docs/assets/js/2925.76671e8e.js"
        }
      ]
    },
    "2983": {
      "js": [
        {
          "file": "assets/js/2983.c66f0ff3.js",
          "hash": "6fcdb39bc0b92a06",
          "publicPath": "/docs/assets/js/2983.c66f0ff3.js"
        }
      ]
    },
    "3068": {
      "js": [
        {
          "file": "assets/js/3068.1a8e5b21.js",
          "hash": "f279c9bf16b91102",
          "publicPath": "/docs/assets/js/3068.1a8e5b21.js"
        }
      ]
    },
    "3626": {
      "js": [
        {
          "file": "assets/js/3626.d3fc7c1d.js",
          "hash": "ae6b27ecc61affce",
          "publicPath": "/docs/assets/js/3626.d3fc7c1d.js"
        }
      ]
    },
    "3706": {
      "js": [
        {
          "file": "assets/js/3706.e60ee3b6.js",
          "hash": "9512f0762b4b9cec",
          "publicPath": "/docs/assets/js/3706.e60ee3b6.js"
        }
      ]
    },
    "4059": {
      "js": [
        {
          "file": "assets/js/10fc90d5.b26a984a.js",
          "hash": "b5b4855cfb849379",
          "publicPath": "/docs/assets/js/10fc90d5.b26a984a.js"
        }
      ]
    },
    "4162": {
      "js": [
        {
          "file": "assets/js/4162.ae2c6b9a.js",
          "hash": "880e34aa93d0bd17",
          "publicPath": "/docs/assets/js/4162.ae2c6b9a.js"
        }
      ]
    },
    "4707": {
      "js": [
        {
          "file": "assets/js/04076d1f.43c8fb7b.js",
          "hash": "f92bfa96c1d2ba32",
          "publicPath": "/docs/assets/js/04076d1f.43c8fb7b.js"
        }
      ]
    },
    "4741": {
      "js": [
        {
          "file": "assets/js/4741.27c3d413.js",
          "hash": "f587c0903e7dcf93",
          "publicPath": "/docs/assets/js/4741.27c3d413.js"
        }
      ]
    },
    "4943": {
      "js": [
        {
          "file": "assets/js/4943.77a21a2f.js",
          "hash": "fadb7f34a03b28d5",
          "publicPath": "/docs/assets/js/4943.77a21a2f.js"
        }
      ]
    },
    "5354": {
      "js": [
        {
          "file": "assets/js/runtime~main.059d9af0.js",
          "hash": "bc1e4300e9ab41f1",
          "publicPath": "/docs/assets/js/runtime~main.059d9af0.js"
        }
      ]
    },
    "5742": {
      "js": [
        {
          "file": "assets/js/aba21aa0.ed09cce9.js",
          "hash": "d58b698fa6accc38",
          "publicPath": "/docs/assets/js/aba21aa0.ed09cce9.js"
        }
      ]
    },
    "5815": {
      "js": [
        {
          "file": "assets/js/7ea72f97.ba59776d.js",
          "hash": "9bcf2bbe9a11dca7",
          "publicPath": "/docs/assets/js/7ea72f97.ba59776d.js"
        }
      ]
    },
    "6061": {
      "js": [
        {
          "file": "assets/js/1f391b9e.602fcab2.js",
          "hash": "cbe4b4a584228dec",
          "publicPath": "/docs/assets/js/1f391b9e.602fcab2.js"
        }
      ]
    },
    "6420": {
      "js": [
        {
          "file": "assets/js/6420.3a5f6ea9.js",
          "hash": "d245516da6baf506",
          "publicPath": "/docs/assets/js/6420.3a5f6ea9.js"
        }
      ]
    },
    "6788": {
      "js": [
        {
          "file": "assets/js/6788.dc6245a1.js",
          "hash": "2d010416079ee1ab",
          "publicPath": "/docs/assets/js/6788.dc6245a1.js"
        }
      ]
    },
    "6803": {
      "js": [
        {
          "file": "assets/js/6803.f9162dd5.js",
          "hash": "f5198215af287966",
          "publicPath": "/docs/assets/js/6803.f9162dd5.js"
        }
      ]
    },
    "6908": {
      "js": [
        {
          "file": "assets/js/cc1bb06d.c8f37d5b.js",
          "hash": "100a4e491d2ea7dc",
          "publicPath": "/docs/assets/js/cc1bb06d.c8f37d5b.js"
        }
      ]
    },
    "7098": {
      "js": [
        {
          "file": "assets/js/a7bd4aaa.73b0e486.js",
          "hash": "6f2219b2beb6e0dc",
          "publicPath": "/docs/assets/js/a7bd4aaa.73b0e486.js"
        }
      ]
    },
    "7426": {
      "js": [
        {
          "file": "assets/js/7426.be6733b9.js",
          "hash": "a1fe47d4f63cd6eb",
          "publicPath": "/docs/assets/js/7426.be6733b9.js"
        }
      ]
    },
    "7502": {
      "js": [
        {
          "file": "assets/js/5931b71a.3925ab4c.js",
          "hash": "ff2ed5dcb5745c7c",
          "publicPath": "/docs/assets/js/5931b71a.3925ab4c.js"
        }
      ]
    },
    "7532": {
      "js": [
        {
          "file": "assets/js/6d49b80b.502b9007.js",
          "hash": "6fd21d048eb0290e",
          "publicPath": "/docs/assets/js/6d49b80b.502b9007.js"
        }
      ]
    },
    "7560": {
      "js": [
        {
          "file": "assets/js/7560.e831fd53.js",
          "hash": "49acab8d8b806bf4",
          "publicPath": "/docs/assets/js/7560.e831fd53.js"
        }
      ]
    },
    "7795": {
      "js": [
        {
          "file": "assets/js/f3976560.76f38087.js",
          "hash": "5345ee6e5d53b7fc",
          "publicPath": "/docs/assets/js/f3976560.76f38087.js"
        }
      ]
    },
    "8055": {
      "js": [
        {
          "file": "assets/js/8055.344fc448.js",
          "hash": "6c906ae15e02a15d",
          "publicPath": "/docs/assets/js/8055.344fc448.js"
        }
      ]
    },
    "8119": {
      "js": [
        {
          "file": "assets/js/20d0fad5.05142dd8.js",
          "hash": "e95d88a799585e5a",
          "publicPath": "/docs/assets/js/20d0fad5.05142dd8.js"
        }
      ]
    },
    "8401": {
      "js": [
        {
          "file": "assets/js/17896441.55bb3e24.js",
          "hash": "0212dfff916b4712",
          "publicPath": "/docs/assets/js/17896441.55bb3e24.js"
        }
      ]
    },
    "8478": {
      "js": [
        {
          "file": "assets/js/8478.bd5b6660.js",
          "hash": "f5c5096d91718b47",
          "publicPath": "/docs/assets/js/8478.bd5b6660.js"
        }
      ]
    },
    "8635": {
      "js": [
        {
          "file": "assets/js/8635.64f37b70.js",
          "hash": "d1491e044ef9eab6",
          "publicPath": "/docs/assets/js/8635.64f37b70.js"
        }
      ]
    },
    "8792": {
      "js": [
        {
          "file": "assets/js/main.dbfc3c91.js",
          "hash": "a3be82e2c9137ce4",
          "publicPath": "/docs/assets/js/main.dbfc3c91.js"
        }
      ]
    },
    "8810": {
      "js": [
        {
          "file": "assets/js/8810.2a33d662.js",
          "hash": "8be574c8bb019214",
          "publicPath": "/docs/assets/js/8810.2a33d662.js"
        }
      ]
    },
    "8869": {
      "js": [
        {
          "file": "assets/js/8869.df783429.js",
          "hash": "e90f22f2e5f0c0f3",
          "publicPath": "/docs/assets/js/8869.df783429.js"
        }
      ]
    },
    "8889": {
      "js": [
        {
          "file": "assets/js/0ec67276.aaafcdfb.js",
          "hash": "4a2368d33f496dae",
          "publicPath": "/docs/assets/js/0ec67276.aaafcdfb.js"
        }
      ]
    },
    "9048": {
      "js": [
        {
          "file": "assets/js/a94703ab.3ccdcad7.js",
          "hash": "416a8d89e3f0068a",
          "publicPath": "/docs/assets/js/a94703ab.3ccdcad7.js"
        }
      ]
    },
    "9319": {
      "js": [
        {
          "file": "assets/js/bbc370a0.53825e69.js",
          "hash": "b14532a06a32881a",
          "publicPath": "/docs/assets/js/bbc370a0.53825e69.js"
        }
      ]
    },
    "9647": {
      "js": [
        {
          "file": "assets/js/5e95c892.cb636bd3.js",
          "hash": "19070b0606096180",
          "publicPath": "/docs/assets/js/5e95c892.cb636bd3.js"
        }
      ]
    },
    "9689": {
      "js": [
        {
          "file": "assets/js/9689.4b5fc7ef.js",
          "hash": "ee8e8054d071ee91",
          "publicPath": "/docs/assets/js/9689.4b5fc7ef.js"
        }
      ]
    }
  }
}